thispkg/__init__.py
thispkg/base/__init__.py
thispkg/base/quipubase.cpp
thispkg/base/quipubase.pyi
thispkg/base/quipubase.pyx
thispkg/base/setup.py
thispkg/base64/__init__.py
thispkg/base64/fast_base64.c
thispkg/base64/fast_base64.pyi
thispkg/base64/setup.py
thispkg/cli.py
thispkg/docs/__init__.py
thispkg/docs/_base.py
thispkg/docs/load_docx.py
thispkg/docs/load_html.py
thispkg/docs/load_img.py
thispkg/docs/load_jsonl.py
thispkg/docs/load_markdown.py
thispkg/docs/load_pdf.py
thispkg/docs/load_pptx.py
thispkg/docs/load_xlsx.py
thispkg/odm.py
thispkg/ouid/__init__.py
thispkg/ouid/ouid.c
thispkg/ouid/ouid.pyi
thispkg/ouid/setup.py
thispkg/schema/__init__.py
thispkg/schema/vector_store_files.py
thispkg/schema/vector_stores.py
thispkg/search_tool.py
thispkg/similarity_search/__init__.py
thispkg/similarity_search/setup.py
thispkg/similarity_search/similarity_search.c
thispkg/similarity_search/similarity_search.pyi
thispkg/utils.py
thispkg-0.0.2.dist-info/METADATA
thispkg-0.0.2.dist-info/WHEEL
thispkg-0.0.2.dist-info/entry_points.txt
thispkg-0.0.2.dist-info/RECORD
