Metadata-Version: 2.1
Name: thispkg
Version: 0.0.2
Summary: 
Author: obahamonde
Author-email: oscar.bahamonde@indiecloud.co
Requires-Python: >=3.10,<4.0
Classifier: Programming Language :: Python :: 3
Classifier: Programming Language :: Python :: 3.10
Classifier: Programming Language :: Python :: 3.11
Classifier: Programming Language :: Python :: 3.12
Requires-Dist: bs4 (>=0.0.2,<0.0.3)
Requires-Dist: cachetools (>=5.5.0,<6.0.0)
Requires-Dist: cython (>=3.0.11,<4.0.0)
Requires-Dist: lxml (>=5.3.0,<6.0.0)
Requires-Dist: numpy (>=1.23.0,<2.0.0)
Requires-Dist: openpyxl (>=3.1.5,<4.0.0)
Requires-Dist: orjson (>=3.10.7,<4.0.0)
Requires-Dist: pillow (>=10.4.0,<11.0.0)
Requires-Dist: pydantic (>=2.8.2,<3.0.0)
Requires-Dist: pymupdf (>=1.24.9,<2.0.0)
Requires-Dist: pypdf2 (>=3.0.1,<4.0.0)
Requires-Dist: python-docx (>=1.1.2,<2.0.0)
Requires-Dist: python-pptx (>=1.0.2,<2.0.0)
Requires-Dist: spacy (>=3.5.0,<4.0.0)
